README.md
setup.py
nwutils/__init__.py
nwutils/batched.py
nwutils/bbox.py
nwutils/data.py
nwutils/data_structures.py
nwutils/dict.py
nwutils/h5py.py
nwutils/index.py
nwutils/kps.py
nwutils/list.py
nwutils/logger.py
nwutils/numpy.py
nwutils/nwmodule.py
nwutils/path.py
nwutils/pickle.py
nwutils/pretty_print.py
nwutils/torch.py
nwutils/type.py
nwutils/unreal.py
nwutils.egg-info/PKG-INFO
nwutils.egg-info/SOURCES.txt
nwutils.egg-info/dependency_links.txt
nwutils.egg-info/top_level.txt
nwutils/others/__init__.py
nwutils/others/fake_args.py
nwutils/others/nwgenerator.py
nwutils/others/others.py
nwutils/others/running_mean.py
nwutils/others/topological_sort.py
test/test_h5py.py
test/test_list.py