Metadata-Version: 2.1
Name: nwutils
Version: 0.3.2
Summary: Generic Utility functions for various projects
Home-page: https://gitlab.com/neuralwrappers/nwutils
Author: Mihai Cristian Pîrvu
Author-email: mihaicristianpirvu@gmail.com
License: WTFPL
Keywords: utilities,utils,high level api
Platform: UNKNOWN
Classifier: Programming Language :: Python :: 3
Classifier: Operating System :: OS Independent
Requires-Python: >=3.7
